holoscan_cu13-3.10.0.data/purelib/holoscan_cu13-3.10.0.pth
holoscan_cu13-3.10.0.data/purelib/holoscan/__init__.py
holoscan_cu13-3.10.0.data/purelib/holoscan/decorator.py
holoscan_cu13-3.10.0.data/purelib/holoscan/cli/__main__.py
holoscan_cu13-3.10.0.data/purelib/holoscan/conditions/__init__.py
holoscan_cu13-3.10.0.data/purelib/holoscan/conditions/_conditions.cpython-313-x86_64-linux-gnu.so
holoscan_cu13-3.10.0.data/purelib/holoscan/core/__init__.py
holoscan_cu13-3.10.0.data/purelib/holoscan/core/_core.cpython-313-x86_64-linux-gnu.so
holoscan_cu13-3.10.0.data/purelib/holoscan/data_loggers/__init__.py
holoscan_cu13-3.10.0.data/purelib/holoscan/data_loggers/async_console_logger/__init__.py
holoscan_cu13-3.10.0.data/purelib/holoscan/data_loggers/async_console_logger/_async_console_logger.cpython-313-x86_64-linux-gnu.so
holoscan_cu13-3.10.0.data/purelib/holoscan/data_loggers/basic_console_logger/__init__.py
holoscan_cu13-3.10.0.data/purelib/holoscan/data_loggers/basic_console_logger/_basic_console_logger.cpython-313-x86_64-linux-gnu.so
holoscan_cu13-3.10.0.data/purelib/holoscan/executors/__init__.py
holoscan_cu13-3.10.0.data/purelib/holoscan/executors/_executors.cpython-313-x86_64-linux-gnu.so
holoscan_cu13-3.10.0.data/purelib/holoscan/graphs/__init__.py
holoscan_cu13-3.10.0.data/purelib/holoscan/graphs/_graphs.cpython-313-x86_64-linux-gnu.so
holoscan_cu13-3.10.0.data/purelib/holoscan/gxf/__init__.py
holoscan_cu13-3.10.0.data/purelib/holoscan/gxf/_gxf.cpython-313-x86_64-linux-gnu.so
holoscan_cu13-3.10.0.data/purelib/holoscan/lib/libgdrapi.so.2.5
holoscan_cu13-3.10.0.data/purelib/holoscan/lib/libgxf_app.so
holoscan_cu13-3.10.0.data/purelib/holoscan/lib/libgxf_core.so
holoscan_cu13-3.10.0.data/purelib/holoscan/lib/libgxf_cuda.so
holoscan_cu13-3.10.0.data/purelib/holoscan/lib/libgxf_logger.so
holoscan_cu13-3.10.0.data/purelib/holoscan/lib/libgxf_multimedia.so
holoscan_cu13-3.10.0.data/purelib/holoscan/lib/libgxf_rmm.so
holoscan_cu13-3.10.0.dist-info/LICENSE.txt
holoscan_cu13-3.10.0.dist-info/METADATA
holoscan_cu13-3.10.0.dist-info/NOTICE.txt
holoscan_cu13-3.10.0.dist-info/NVIDIA-AI-PRODUCT-EULA.txt
holoscan_cu13-3.10.0.dist-info/README.md
holoscan_cu13-3.10.0.dist-info/WHEEL
holoscan_cu13-3.10.0.dist-info/axle.lck
holoscan_cu13-3.10.0.dist-info/symlinks.txt
holoscan_cu13-3.10.0.dist-info/top_level.txt
holoscan_cu13-3.10.0.dist-info/RECORD
